control_unit/sign_extend/sign_extend.sv
/* verilator lint_off UNUSED */
module sign_extend #(
    parameter   DATA_WIDTH = 32,
                IMM_WIDTH = 12
)(
    input   logic [DATA_WIDTH-1:0]  instr,
    input   logic [IMM_WIDTH-1:0]   ImmSrc,    
    output  logic [DATA_WIDTH-1:0]  ImmOp
);


    always_comb 
        begin
            case ({instr[6:0],instr[14:12]})
            if ({instr[6:0],instr[14:12]} == 10'b0010011000 && ImmSrc[11]==1'b1)
                ImmOp = {20'b11111111111111111111, ImmSrc};
            else
                ImmOp = {20'b0, ImmSrc};
            endcase
        end


endmodule

control_unit/sign_extend/sign_extend.vcd
$version Generated by VerilatedVcd $end
$date Sat Nov 19 00:18:45 2022 $end
$timescale 1ps $end

 $scope module TOP $end
  $var wire 32 % ImmOp [31:0] $end
  $var wire 12 $ ImmSrc [11:0] $end
  $var wire 32 # instr [31:0] $end
  $scope module sign_extend $end
   $var wire 32 & DATA_WIDTH [31:0] $end
   $var wire 32 ' IMM_WIDTH [31:0] $end
   $var wire 32 % ImmOp [31:0] $end
   $var wire 12 $ ImmSrc [11:0] $end
   $var wire 32 # instr [31:0] $end
  $upscope $end
 $upscope $end
$enddefinitions $end


#0
b11111110000000110001100011100011 #
b111111111111 $
b00000000000000000000000000000000 %
b00000000000000000000000000100000 &
b00000000000000000000000000001100 '
#2
b00000000000101011000010110010011 #
b00000000000000000000111111111111 %
#4
b11111111111111111111111111111111 %
#6
b11111110000000110001100011100011 #
#8
b00000000000000000000111111111111 %
#10
b00000000000000000000000000010011 #
#12
b11111111111111111111111111111111 %
#14
b00000000000101011000010110010011 #
#16
#18
b01111101000000001010000100010011 #
#20
b00000000000000000000111111111111 %
#22
b11111110000000110001100011100011 #
